{
    "created": 1758129258.088254,
    "duration": 53.14340806007385,
    "exitcode": 0,
    "root": "/mnt/devel/george/work/rs_ats/rs_ats_sw/tests_automation",
    "environment": {},
    "summary": {
        "passed": 2,
        "total": 2,
        "collected": 2
    },
    "collectors": [
        {
            "nodeid": "",
            "outcome": "passed",
            "result": [
                {
                    "nodeid": "::test_socan_normal_mode",
                    "type": "Function",
                    "lineno": 511
                },
                {
                    "nodeid": "::test_setup_updown_fwd",
                    "type": "Function",
                    "lineno": 494
                }
            ]
        }
    ],
    "tests": [
        {
            "nodeid": "::test_socan_normal_mode",
            "lineno": 511,
            "outcome": "passed",
            "keywords": [
                "test_socan_normal_mode",
                "test_v1_1.py",
                "tests",
                "setups",
                "general",
                "nucom_gen1",
                "rs_ats_tests",
                ""
            ],
            "setup": {
                "duration": 1.439294486073777,
                "outcome": "passed"
            },
            "call": {
                "duration": 0.03210330195724964,
                "outcome": "passed"
            },
            "teardown": {
                "duration": 0.03968647704459727,
                "outcome": "passed"
            }
        },
        {
            "nodeid": "::test_setup_updown_fwd",
            "lineno": 494,
            "outcome": "passed",
            "keywords": [
                "test_setup_updown_fwd",
                "test_v1_1.py",
                "tests",
                "setups",
                "general",
                "nucom_gen1",
                "rs_ats_tests",
                ""
            ],
            "setup": {
                "duration": 0.006613492034375668,
                "outcome": "passed"
            },
            "call": {
                "duration": 50.88078421493992,
                "outcome": "passed"
            },
            "teardown": {
                "duration": 0.0027974139666184783,
                "outcome": "passed"
            }
        }
    ]
}